{
  "moduleid": "microservice-resources-config",
  "type": "config",
  "url": "github.com:vicjicaman/microservice-resources-config.git",
  "fullname": "github.com:vicjicaman/microservice-resources-config.git",
  "iteration": {
    "mode": "prod"
  },
  "release": {
    "type": "patch"
  },
  "description": "Configuration for the common resources service",
  "created": 1570150226,
  "updated": 1570150226,
  "status": "active",
  "commit": {
    "commitid": "a93e9a282b2812b0aa3d24ee38e3ad81f4b89dee",
    "message": "Add blog realm and modifications to resources realm and config issue\n"
  }
}