{
  "moduleid": "microservice-auth-cache",
  "type": "stateful",
  "url": "github.com:vicjicaman/microservice-auth-cache.git",
  "fullname": "microservice-auth-cache",
  "iteration": {
    "mode": "prod"
  },
  "release": {
    "type": "patch"
  },
  "description": "Redis service to store auth sessions",
  "created": 1568481986,
  "updated": 1568481986,
  "status": "active",
  "commit": {
    "commitid": "68a159f99d6dc62634c67d3bcdab037ba169f93d",
    "message": "Separate pre/post process of instancification of kubernetes entities\n"
  }
}