{
  "moduleid": "microservice-home",
  "type": "npm",
  "url": "github.com:vicjicaman/microservice-home.git",
  "fullname": "@nebulario/microservice-home",
  "iteration": {
    "mode": "prod"
  },
  "release": {
    "type": "patch"
  },
  "description": "Home service app/code for microservices with Kubernetes",
  "created": 1568561725,
  "updated": 1568561725,
  "status": "active",
  "commit": {
    "commitid": "01e5a848429436abca8bbf5eb5caf8142e27ab59",
    "message": "Add initial home web and graph services\n"
  }
}