{
  "releaseid": "blog-home",
  "moduleid": "microservice-namespace",
  "version": "1.70.7-master",
  "fullname": "microservice-namespace",
  "type": "namespace",
  "url": "github.com:vicjicaman/microservice-namespace.git",
  "publish": null,
  "released": {
    "commitid": "45c3bb3695c487f6ccce4c08ecdba651a4472e30",
    "message": "ITERATION:7\n"
  },
  "mergeback": null,
  "releaseType": "patch",
  "description": "Namespace for the microservices demo",
  "dependencies": [],
  "created": 1569448931,
  "updated": 1569448931,
  "status": "active"
}