{
  "moduleid": "microservice-blog-web-service",
  "type": "service",
  "url": "github.com:vicjicaman/microservice-blog-web-service.git",
  "fullname": "microservice-blog-web-service",
  "iteration": {
    "mode": "prod"
  },
  "release": {
    "type": "patch"
  },
  "description": "Web service for the blog UI",
  "created": 1568772266,
  "updated": 1568772266,
  "status": "active",
  "commit": {
    "commitid": "68d230b7c82f9ac327203675cc12e5b3848a5b6f",
    "message": "Add article editor\n"
  }
}