{
  "releaseid": "blog-comments",
  "moduleid": "microservice-auth-graph-container",
  "version": "1.70.8-master",
  "fullname": "repoflow/microservice-auth-graph-container",
  "type": "container",
  "url": "github.com:vicjicaman/microservice-auth-graph-container.git",
  "publish": null,
  "released": {
    "commitid": "4965792dbbaec95169fe410655b0fa373db75de4",
    "message": "ITERATION:1\n"
  },
  "mergeback": null,
  "releaseType": "patch",
  "description": "Container for the auth graph",
  "dependencies": [],
  "created": 1572318554,
  "updated": 1572318554,
  "status": "active"
}